verilog/full_adder.v
`timescale 1ns/1ps

module full_adder (
    input  wire a,
    input  wire b,
    input  wire cin,
    output wire sum,
    output wire cout
);

    // Full adder logic
    assign sum  = a ^ b ^ cin;
    assign cout = (a & b) | (b & cin) | (a & cin);

endmodule

verilog/tb_full_adder.v
`timescale 1ns/1ps

`include "full_adder.v"

module tb_full_adder;

    reg a;
    reg b;
    reg cin;
    wire sum;
    wire cout;

    // Instantiate DUT (Device Under Test)
    full_adder dut (
        .a(a),
        .b(b),
        .cin(cin),
        .sum(sum),
        .cout(cout)
    );

    initial begin
        // Dump waveform
        $dumpfile("full_adder.vcd");
        $dumpvars(0, tb_full_adder);

        // Display header
        $display("A B Cin | Sum Cout");
        $display("------------------");

        // Apply all input combinations
        a=0; b=0; cin=0; #10; $display("%b %b  %b  |  %b    %b", a,b,cin,sum,cout);
        a=0; b=0; cin=1; #10; $display("%b %b  %b  |  %b    %b", a,b,cin,sum,cout);
        a=0; b=1; cin=0; #10; $display("%b %b  %b  |  %b    %b", a,b,cin,sum,cout);
        a=0; b=1; cin=1; #10; $display("%b %b  %b  |  %b    %b", a,b,cin,sum,cout);
        a=1; b=0; cin=0; #10; $display("%b %b  %b  |  %b    %b", a,b,cin,sum,cout);
        a=1; b=0; cin=1; #10; $display("%b %b  %b  |  %b    %b", a,b,cin,sum,cout);
        a=1; b=1; cin=0; #10; $display("%b %b  %b  |  %b    %b", a,b,cin,sum,cout);
        a=1; b=1; cin=1; #10; $display("%b %b  %b  |  %b    %b", a,b,cin,sum,cout);

        #10;
        $finish;
    end

endmodule

verilog/full_adder.vcd
$date
	Tue Feb 17 14:36:47 2026
$end
$version
	Icarus Verilog
$end
$timescale
	1ps
$end
$scope module tb_full_adder $end
$var wire 1 ! sum $end
$var wire 1 " cout $end
$var reg 1 # a $end
$var reg 1 $ b $end
$var reg 1 % cin $end
$scope module dut $end
$var wire 1 # a $end
$var wire 1 $ b $end
$var wire 1 % cin $end
$var wire 1 " cout $end
$var wire 1 ! sum $end
$upscope $end
$upscope $end
$enddefinitions $end
$comment Show the parameter values. $end
$dumpall
$end
#0
$dumpvars
0%
0$
0#
0"
0!
$end
#10000
1!
1%
#20000
0%
1$
#30000
1"
0!
1%
#40000
0"
1!
0%
0$
1#
#50000
1"
0!
1%
#60000
0%
1$
#70000
1!
1%
